pyform/__init__.py
pyform/_version.py
pyform/returnseries.py
pyform/timeseries.py
pyform/analysis/__init__.py
pyform/analysis/returns.py
pyform/returns/__init__.py
pyform/returns/compound.py
pyform/returns/metrics.py
pyform/util/__init__.py
pyform/util/dataframe.py
pyform/util/freq.py
tests/__init__.py
tests/unit/__init__.py
tests/unit/test_returnseries.py
tests/unit/test_timeseries.py
pyform-0.0.10.dist-info/LICENSE
pyform-0.0.10.dist-info/METADATA
pyform-0.0.10.dist-info/WHEEL
pyform-0.0.10.dist-info/top_level.txt
pyform-0.0.10.dist-info/RECORD
