Metadata-Version: 2.1
Name: pyform
Version: 0.0.10
Summary: An event-driven algorithmic trading framework
Home-page: https://github.com/shawnlinxl/pyform
Author: Shawn Lin
Author-email: shawn.lin@gatech.edu
License: UNKNOWN
Platform: UNKNOWN
Classifier: Programming Language :: Python :: 3
Classifier: License :: OSI Approved :: MIT License
Classifier: Operating System :: OS Independent
Requires-Python: >=3.6
Requires-Dist: pandas (>=1.0.0)
